{"title":"김밥레코즈 ─ CD ─ Jazz","url":"http://gimbabrecords.com/product/list.html?cate_no=46","favicon":"http://gimbabrecords.com/product/favicon.ico","elements":[{"title":"Pat Metheny Group / Speaking Of Now (CD) *절판된 시디 마지막 재고","contents":"19,000원","link":"http://gimbabrecords.com/product/detail.html?product_no=25053&cate_no=46&display_group=1","retrieved":1713031797982,"image":"http://gimbabrecords.com/web/product/medium/202404/0e0b7073bfe429821095229cd4ff26ed.jpg"},{"title":"Andre 3000 / New Blue Sun (2CD) *예약 주문 (4월 16일까지 결제가 완료된 주문은 4월 26일경 배송이 진행될 예정입니다.)","contents":"38,000원","link":"http://gimbabrecords.com/product/detail.html?product_no=25052&cate_no=46&display_group=1","retrieved":1713081067724,"image":"http://gimbabrecords.com/web/product/medium/202404/15a1fea32a7a708da658c1a4e36a7019.jpg"},{"title":"Miles Davis & Quincy Jones / Live At Montreux (CD, Japanese remaster, OBI) *한정수량 할인","contents":"12,500원","link":"http://gimbabrecords.com/product/detail.html?product_no=24992&cate_no=46&display_group=1","retrieved":1712139039908,"image":"http://gimbabrecords.com/web/product/medium/202404/90ee74895ba7cba2a8a39c6d22435b3c.jpg"},{"title":"Jaco Pastorius / Word Of Mouth (CD) *한정수량 할인","contents":"12,500원","link":"http://gimbabrecords.com/product/detail.html?product_no=24989&cate_no=46&display_group=1","retrieved":1712139039910,"image":"http://gimbabrecords.com/web/product/medium/201805/10871_shop1_959499.jpg"},{"title":"Terrace Martin, Robert Glasper, 9th Wonder, Kamasi Washington / Dinner Party & Dessert (CD, DIgipak)","contents":"23,500원","link":"http://gimbabrecords.com/product/detail.html?product_no=24938&cate_no=46&display_group=1","retrieved":1711102161533,"image":"http://gimbabrecords.com/web/product/medium/202403/fad65e88d70519e70489334f6703fb8e.jpg"},{"title":"Shakti With John McLaughlin / Natural Elements (CD) *한정수량 할인","contents":"13,500원","link":"http://gimbabrecords.com/product/detail.html?product_no=24896&cate_no=46&display_group=1","retrieved":1710918642794,"image":"http://gimbabrecords.com/web/product/medium/202403/8527f1e07106111ecaf19b7307cacf82.jpg"},{"title":"Laufey / Everything I Know About Love (CD, Digi Gatefold Sleeve)","contents":"25,000원","link":"http://gimbabrecords.com/product/detail.html?product_no=24868&cate_no=46&display_group=1","retrieved":1710497366036,"image":"http://gimbabrecords.com/web/product/medium/202403/b9e73d5e0054d0ed87135d059f1c79a3.jpg"},{"title":"O'Donel Levy / Simba (CD, EU Import)","contents":"26,000원","link":"http://gimbabrecords.com/product/detail.html?product_no=24821&cate_no=46&display_group=1","retrieved":1710227346087,"image":"http://gimbabrecords.com/web/product/medium/202403/04dbcac4d5b5016643402cbcfd4407c1.jpg"},{"title":"Opa / Back Home (CD)","contents":"22,500원","link":"http://gimbabrecords.com/product/detail.html?product_no=24808&cate_no=46&display_group=1","retrieved":1710140984268,"image":"http://gimbabrecords.com/web/product/medium/202403/114001fd0a4a4d07ddfa684a1cd9a605.jpg"},{"title":"Agustin Pereyra Lucena / Agustin Pereyra Lucena (CD)","contents":"22,500원","link":"http://gimbabrecords.com/product/detail.html?product_no=24787&cate_no=46&display_group=1","retrieved":1709809694153,"image":"http://gimbabrecords.com/web/product/medium/202403/7238a3c2fa3e28781a78294ebc4dccd4.jpg"},{"title":"Charles Mingus / Presents Charles Mingus (Remastered CD)","contents":"21,500원","link":"http://gimbabrecords.com/product/detail.html?product_no=24738&cate_no=46&display_group=1","retrieved":1709201353906,"image":"http://gimbabrecords.com/web/product/medium/202402/6fd2d1310fe4329978d0759734c6e17b.jpg"},{"title":"John Zorn / Homenaje A Remedios Varo (CD, Digipak)","contents":"29,700원","link":"http://gimbabrecords.com/product/detail.html?product_no=24737&cate_no=46&display_group=1","retrieved":1709201353906,"image":"http://gimbabrecords.com/web/product/medium/202402/fd7d13ec71d47864431468fed90e3e56.jpg"}]}