{"title":"김밥레코즈 ─ Pre-Order","url":"http://gimbabrecords.com/product/list.html?cate_no=42","favicon":"http://gimbabrecords.com/product/favicon.ico","elements":[{"title":"Kaze Chorus Dan / Aiiro no Kisetsu (Vinyl) *예약상품 (8월초 배송 예정)","contents":"49,000원","link":"http://gimbabrecords.com/product/detail.html?product_no=25348&cate_no=42&display_group=1","retrieved":1715771277588,"image":"https://cafe24img.poxo.com/gimbabrecords/web/product/medium/202405/5adb3eb4ad89c626bf201000072f16b8.jpg"},{"title":"Yuka Noda / Ka Ri Bu No Yu Me : Light Fusion Fantasy (CD) *예약상품 (8월초 배송 예정)","contents":"33,000원","link":"http://gimbabrecords.com/product/detail.html?product_no=25347&cate_no=42&display_group=1","retrieved":1715771277588,"image":"https://cafe24img.poxo.com/gimbabrecords/web/product/medium/202405/022bab68108f34a31f0c9749368c784c.jpg"},{"title":"Yuka Noda / Ka Ri Bu No Yu Me : Light Fusion Fantasy (Vinyl) *예약상품 (8월초 배송 예정)","contents":"45,000원","link":"http://gimbabrecords.com/product/detail.html?product_no=25346&cate_no=42&display_group=1","retrieved":1715771277591,"image":"https://cafe24img.poxo.com/gimbabrecords/web/product/medium/202405/ff8847457b0055c854dcb9ff625f4fdb.jpg"},{"title":"Miki Matsubara / Revue (Clear Red Vinyl) *예약상품 (8월 중순 배송 예정)","contents":"46,000원","link":"http://gimbabrecords.com/product/detail.html?product_no=25345&cate_no=42&display_group=1","retrieved":1715771277591,"image":"https://cafe24img.poxo.com/gimbabrecords/web/product/medium/202405/b4bc71c1164d2b189c00296982dc21ae.jpg"},{"title":"Miki Matsubara / Aya (Clear Red Vinyl) *예약상품 (8월 중순 배송 예정)","contents":"46,000원","link":"http://gimbabrecords.com/product/detail.html?product_no=25344&cate_no=42&display_group=1","retrieved":1715771277596,"image":"https://cafe24img.poxo.com/gimbabrecords/web/product/medium/202405/d5ea9cc8ec3b02c63421005c3dac0ff5.jpg"},{"title":"Jimmy Smith / Root Down (Jimmy Smith Live!) (Vinyl) *예약상품 (5월말 배송 예정)","contents":"44,500원","link":"http://gimbabrecords.com/product/detail.html?product_no=4510&cate_no=42&display_group=1","retrieved":1715490583266,"image":"https://cafe24img.poxo.com/gimbabrecords/web/product/medium/201607/4510_shop1_121186.jpg"},{"title":"OST (Music by Joe Hisaishi, 주제곡 Kenshi Yonezu)  / The Boy And The Heron  그대들은 어떻게 살 것인가 (君たちはどう生きるか ) (Vinyl, 2LP) *예약상품 (7월 중순 배송 예정)","contents":"56,000원","link":"http://gimbabrecords.com/product/detail.html?product_no=25261&cate_no=42&display_group=1","retrieved":1715677807789,"image":"https://cafe24img.poxo.com/gimbabrecords/web/product/medium/202405/e2889f891892ba6150550b7bcc05f684.png"},{"title":"[음반 매장에서 듣는 음악 강의 시리즈 2]  라이브 연주를 통해 배우는 재즈와 라틴 음악 - 재즈 피아니스트 고희안의 연주와 강의를 통해 배우는 재즈의 스타일과 특징 1강) 5월 16일 목요일 저녁 8시  초기 재즈 (스윙)와 빌 에반스","contents":"10,000원","link":"http://gimbabrecords.com/product/detail.html?product_no=25328&cate_no=42&display_group=1","retrieved":1715609325953,"image":"https://cafe24img.poxo.com/gimbabrecords/web/product/medium/202405/8975cc4655eb1086440e82eeefdaff1f.jpg"},{"title":"김뜻돌 / EP 1집 COBALT (Pink Marble Colored Vinyl, 45RPM) *예약상품 (8월 22일 발매 예정, 5월 13일 주문 마감)","contents":"44,600원","link":"http://gimbabrecords.com/product/detail.html?product_no=25257&cate_no=42&display_group=1","retrieved":1715584188583,"image":"https://cafe24img.poxo.com/gimbabrecords/web/product/medium/202404/61277c5cbef6036c1a8c452bc19c1555.jpg"},{"title":"Asami Kado / Anti Fleur (Limited Clear Vinyl) *예약상품 (9월 중순 배송 예정)","contents":"48,500원","link":"http://gimbabrecords.com/product/detail.html?product_no=25327&cate_no=42&display_group=1","retrieved":1715432880985,"image":"https://cafe24img.poxo.com/gimbabrecords/web/product/medium/202405/9449e57cf5a6cc7378b0728edcec8cb5.jpg"},{"title":"Asami Kado / La Fleur Bleue (Limited Clear Sky Blue Vinyl) *예약상품 (9월 중순 배송 예정)","contents":"48,500원","link":"http://gimbabrecords.com/product/detail.html?product_no=25326&cate_no=42&display_group=1","retrieved":1715429618749,"image":"https://cafe24img.poxo.com/gimbabrecords/web/product/medium/202405/ddbc0b85736f749672c2f942f04d374b.jpg"},{"title":"Niningashi / Heavy Way (Vinyl) *예약상품 (5월말 배송 예정)","contents":"41,500원","link":"http://gimbabrecords.com/product/detail.html?product_no=25322&cate_no=42&display_group=1","retrieved":1715429618749,"image":"https://cafe24img.poxo.com/gimbabrecords/web/product/medium/202405/45fa6e650ffdcc906d0620643a1f2d1d.jpg"}]}